linear_series/__init__.py
linear_series/__main__.py
linear_series/class_base_points.py
linear_series/class_linear_series.py
linear_series/class_ls_tools.py
linear_series/class_poly_ring.py
linear_series/get_base_point_tree.py
linear_series/get_implicit.py
linear_series/get_linear_series.py
linear_series/get_solution_set.py
linear_series/sage_interface.py
linear_series/test_tools.sobj
tests/__init__.py
tests/class_test_tools.py
tests/test_class_base_points.py
tests/test_class_linear_series.py
tests/test_class_ls_tools.py
tests/test_class_poly_ring.py
tests/test_get_base_point_tree.py
tests/test_get_implicit.py
tests/test_get_linear_series.py
tests/test_get_solution_set.py
linear_series-8.dist-info/LICENSE
linear_series-8.dist-info/METADATA
linear_series-8.dist-info/WHEEL
linear_series-8.dist-info/entry_points.txt
linear_series-8.dist-info/top_level.txt
linear_series-8.dist-info/RECORD
