Metadata-Version: 2.1
Name: linear-series
Version: 8
Summary: Base point analysis for linear series of curves in the plane.
Home-page: http://github.com/niels-lubbes/linear_series
Author: Niels Lubbes
License: MIT
Keywords: linear series
Platform: UNKNOWN
Classifier: Development Status :: 3 - Alpha
Classifier: License :: OSI Approved :: MIT License
Classifier: Programming Language :: Python :: 3
Classifier: Topic :: Scientific/Engineering :: Mathematics
License-File: LICENSE
